{
  "dex" : 89,
  "speciesId" : "SPECIES_MUK",
  "name" : "Muk",
  "types" : [ "Poison", null ],
  "abilities" : [ "Stench", "Sticky Hold", "Poison Touch" ],
  "evYield" : {
    "hp" : 1,
    "atk" : 1
  },
  "malePct" : 50.0,
  "femalePct" : 50.0,
  "catchRate" : 75,
  "baseExp" : 0,
  "eggGroups" : [ "Amorphous" ],
  "hatchSteps" : 5120,
  "heightM" : 1.2,
  "weightKg" : 30.0,
  "growthRate" : "Medium Fast",
  "color" : "Purple",
  "category" : "Sludge",
  "friendship" : 70,
  "description" : "It prefers warm and humid habitats.\nIn the summertime, the toxic substances\nin its body intensify, making Muk reek like\nputrid kitchen garbage.",
  "preEvolutionId" : "SPECIES_GRIMER",
  "evolution" : [ ],
  "baseStats" : {
    "hp" : 105,
    "atk" : 105,
    "def" : 80,
    "spe" : 50,
    "spa" : 65,
    "spd" : 100
  },
  "heldItems" : {
    "common" : "Black Sludge"
  },
  "levelUpMoves" : [ {
    "level" : 0,
    "move" : "Venom Drench"
  }, {
    "level" : 1,
    "move" : "Harden"
  }, {
    "level" : 1,
    "move" : "Mud Slap"
  }, {
    "level" : 1,
    "move" : "Poison Gas"
  }, {
    "level" : 1,
    "move" : "Pound"
  }, {
    "level" : 1,
    "move" : "Venom Drench"
  }, {
    "level" : 4,
    "move" : "Harden"
  }, {
    "level" : 7,
    "move" : "Mud Slap"
  }, {
    "level" : 12,
    "move" : "Disable"
  }, {
    "level" : 15,
    "move" : "Sludge"
  }, {
    "level" : 18,
    "move" : "Mud Bomb"
  }, {
    "level" : 21,
    "move" : "Minimize"
  }, {
    "level" : 26,
    "move" : "Fling"
  }, {
    "level" : 29,
    "move" : "Sludge Bomb"
  }, {
    "level" : 32,
    "move" : "Poison Fang"
  }, {
    "level" : 37,
    "move" : "Screech"
  }, {
    "level" : 38,
    "move" : "Venom Drench"
  }, {
    "level" : 40,
    "move" : "Gunk Shot"
  }, {
    "level" : 46,
    "move" : "Acid Armor"
  }, {
    "level" : 52,
    "move" : "Belch"
  }, {
    "level" : 57,
    "move" : "Memento"
  } ],
  "eggMoves" : [ "Acid Spray", "Curse", "Haze", "Imprison", "Lick", "Mean Look", "Power Up Punch", "Scary Face", "Shadow Punch", "Shadow Sneak", "Spit Up", "Stockpile", "Swallow" ],
  "teachableMoves" : [ "Attract", "Body Slam", "Brick Break", "Dark Pulse", "Dig", "Double Team", "Drain Punch", "Dynamic Punch", "Endure", "Explosion", "Facade", "Fire Blast", "Fire Punch", "Flamethrower", "Focus Blast", "Giga Drain", "Giga Impact", "Hex", "Hyper Beam", "Ice Punch", "Knock Off", "Metronome", "Mud Slap", "Poison Jab", "Power Up Punch", "Protect", "Rain Dance", "Rest", "Rock Slide", "Rock Smash", "Rock Tomb", "Sandstorm", "Shadow Ball", "Shock Wave", "Sleep Talk", "Sludge Bomb", "Sludge Wave", "Snore", "Strength", "Sunny Day", "Swagger", "Swift", "Taunt", "Thief", "Thunder", "Thunder Punch", "Thunderbolt", "Torment", "Toxic", "Venoshock" ],
  "encounters" : [ {
    "areaKey" : "VictoryRoad_1F",
    "bucketKey" : "Land",
    "area" : "Victory Road_1F",
    "bucket" : "Land",
    "rateBase" : 4,
    "min" : 79,
    "max" : 85,
    "slot" : 4
  } ]
}