{
  "dex" : 177,
  "speciesId" : "SPECIES_LEDYBA",
  "name" : "Ledyba",
  "types" : [ "Bug", "Flying" ],
  "abilities" : [ "Swarm", "Early Bird", "Rattled" ],
  "evYield" : {
    "spd" : 1
  },
  "malePct" : 50.0,
  "femalePct" : 50.0,
  "catchRate" : 255,
  "baseExp" : 0,
  "eggGroups" : [ "Bug" ],
  "hatchSteps" : 3840,
  "heightM" : 1.0,
  "weightKg" : 10.8,
  "growthRate" : "Fast",
  "color" : "Red",
  "category" : "Five Star",
  "friendship" : 70,
  "description" : "Ledyba communicate using a fluid that\nthey secrete from where the legs join the\nbody. They are said to convey feelings to\nothers by altering the fluid's scent.",
  "preEvolutionId" : null,
  "evolution" : [ {
    "toSpeciesId" : "SPECIES_LEDIAN",
    "method" : "level",
    "param" : "18"
  } ],
  "baseStats" : {
    "hp" : 40,
    "atk" : 20,
    "def" : 30,
    "spe" : 55,
    "spa" : 40,
    "spd" : 80
  },
  "heldItems" : { },
  "levelUpMoves" : [ {
    "level" : 1,
    "move" : "Tackle"
  }, {
    "level" : 5,
    "move" : "Supersonic"
  }, {
    "level" : 8,
    "move" : "Swift"
  }, {
    "level" : 12,
    "move" : "Light Screen"
  }, {
    "level" : 12,
    "move" : "Reflect"
  }, {
    "level" : 12,
    "move" : "Safeguard"
  }, {
    "level" : 15,
    "move" : "Mach Punch"
  }, {
    "level" : 19,
    "move" : "Roost"
  }, {
    "level" : 22,
    "move" : "Struggle Bug"
  }, {
    "level" : 26,
    "move" : "Baton Pass"
  }, {
    "level" : 29,
    "move" : "Agility"
  }, {
    "level" : 33,
    "move" : "Bug Buzz"
  }, {
    "level" : 36,
    "move" : "Air Slash"
  }, {
    "level" : 40,
    "move" : "Double Edge"
  } ],
  "eggMoves" : [ "Bide", "Bug Bite", "Bug Buzz", "Counter", "Dizzy Punch", "Drain Punch", "Encore", "Endure", "Focus Punch", "Knock Off", "Psybeam", "Screech", "Silver Wind", "Tailwind" ],
  "teachableMoves" : [ "Acrobatics", "Aerial Ace", "Air Slash", "Attract", "Brick Break", "Counter", "Dig", "Double Edge", "Double Team", "Drain Punch", "Dynamic Punch", "Endure", "Facade", "Flash", "Giga Drain", "Ice Punch", "Knock Off", "Light Screen", "Mega Punch", "Power Up Punch", "Protect", "Reflect", "Rest", "Rollout", "Roost", "Safeguard", "Silver Wind", "Sleep Talk", "Snore", "Solar Beam", "Sunny Day", "Swagger", "Swift", "Swords Dance", "Thief", "Thunder Punch", "Toxic", "U Turn" ],
  "encounters" : [ {
    "area" : "Route 104",
    "bucket" : "Land",
    "rateBase" : 20,
    "min" : 6,
    "max" : 7,
    "slot" : 4
  }, {
    "area" : "Route 104",
    "bucket" : "Land",
    "rateBase" : 20,
    "min" : 6,
    "max" : 7,
    "slot" : 7
  }, {
    "area" : "Safari Zone_Northeast",
    "bucket" : "Land",
    "rateBase" : 25,
    "min" : 33,
    "max" : 33,
    "slot" : 5
  } ]
}