{
  "dex" : 180,
  "speciesId" : "SPECIES_ARIADOS",
  "name" : "Ariados",
  "types" : [ "Bug", "Poison" ],
  "abilities" : [ "Swarm", "Insomnia", "Sniper" ],
  "evYield" : {
    "atk" : 2
  },
  "malePct" : 50.0,
  "femalePct" : 50.0,
  "catchRate" : 90,
  "baseExp" : 134,
  "eggGroups" : [ "Bug" ],
  "hatchSteps" : 3840,
  "heightM" : 1.1,
  "weightKg" : 33.5,
  "growthRate" : "Fast",
  "color" : "Red",
  "category" : "Long Leg",
  "friendship" : 70,
  "description" : "Its feet are tipped with tiny hooked claws\nthat enable it to scuttle on ceilings and\nvertical walls. It constricts its foe with\nthin and strong silk webbing.",
  "preEvolutionId" : "SPECIES_SPINARAK",
  "evolution" : [ ],
  "baseStats" : {
    "hp" : 100,
    "atk" : 90,
    "def" : 70,
    "spe" : 40,
    "spa" : 60,
    "spd" : 80
  },
  "heldItems" : { },
  "levelUpMoves" : [ {
    "level" : 0,
    "move" : "Swords Dance"
  }, {
    "level" : 1,
    "move" : "Absorb"
  }, {
    "level" : 1,
    "move" : "Bug Bite"
  }, {
    "level" : 1,
    "move" : "Constrict"
  }, {
    "level" : 1,
    "move" : "Fell Stinger"
  }, {
    "level" : 1,
    "move" : "Focus Energy"
  }, {
    "level" : 1,
    "move" : "Poison Sting"
  }, {
    "level" : 1,
    "move" : "String Shot"
  }, {
    "level" : 1,
    "move" : "Swords Dance"
  }, {
    "level" : 1,
    "move" : "Venom Drench"
  }, {
    "level" : 5,
    "move" : "Absorb"
  }, {
    "level" : 8,
    "move" : "Infestation"
  }, {
    "level" : 12,
    "move" : "Scary Face"
  }, {
    "level" : 15,
    "move" : "Night Shade"
  }, {
    "level" : 22,
    "move" : "Swords Dance"
  }, {
    "level" : 23,
    "move" : "Fury Swipes"
  }, {
    "level" : 28,
    "move" : "Sucker Punch"
  }, {
    "level" : 30,
    "move" : "Spider Web"
  }, {
    "level" : 32,
    "move" : "Agility"
  }, {
    "level" : 34,
    "move" : "Pin Missile"
  }, {
    "level" : 37,
    "move" : "Poison Jab"
  }, {
    "level" : 42,
    "move" : "Gunk Shot"
  }, {
    "level" : 46,
    "move" : "Psychic"
  }, {
    "level" : 49,
    "move" : "Megahorn"
  }, {
    "level" : 54,
    "move" : "Sticky Web"
  }, {
    "level" : 63,
    "move" : "Toxic Thread"
  } ],
  "eggMoves" : [ "Baton Pass", "Disable", "Electroweb", "Lunge", "Megahorn", "Night Slash", "Psybeam", "Pursuit", "Rage Powder", "Signal Beam", "Sonic Boom", "Toxic Spikes", "Twineedle" ],
  "teachableMoves" : [ "Attract", "Body Slam", "Dig", "Double Edge", "Double Team", "Electroweb", "Endure", "Facade", "Flash", "Giga Drain", "Giga Impact", "Hex", "Hone Claws", "Hyper Beam", "Knock Off", "Leech Life", "Poison Jab", "Protect", "Psychic", "Rest", "Sleep Talk", "Sludge Bomb", "Sludge Wave", "Smart Strike", "Snore", "Solar Beam", "Sunny Day", "Swagger", "Swords Dance", "Thief", "Toxic", "Trailblaze", "Venoshock", "X Scissor" ],
  "encounters" : [ {
    "areaKey" : "Route119",
    "bucketKey" : "Land",
    "area" : "Route 119",
    "bucket" : "Land",
    "rateBase" : 15,
    "min" : 50,
    "max" : 54,
    "slot" : 9
  } ]
}