{
  "dex" : 592,
  "speciesId" : "SPECIES_RIBOMBEE",
  "name" : "Ribombee",
  "types" : [ "Bug", "Fairy" ],
  "abilities" : [ "Serene Grace", "Shield Dust", "Sweet Veil" ],
  "evYield" : {
    "spe" : 2
  },
  "malePct" : 50.0,
  "femalePct" : 50.0,
  "catchRate" : 75,
  "baseExp" : 162,
  "eggGroups" : [ "Bug", "Fairy" ],
  "hatchSteps" : 5120,
  "heightM" : 0.2,
  "weightKg" : 0.5,
  "growthRate" : "Medium Fast",
  "color" : "Yellow",
  "category" : "Bee Fly",
  "friendship" : 70,
  "description" : null,
  "preEvolutionId" : "SPECIES_CUTIEFLY",
  "evolution" : [ ],
  "baseStats" : {
    "hp" : 70,
    "atk" : 55,
    "def" : 65,
    "spe" : 124,
    "spa" : 105,
    "spd" : 70
  },
  "heldItems" : {
    "common" : "Honey"
  },
  "levelUpMoves" : [ {
    "level" : 0,
    "move" : "Pollen Puff"
  }, {
    "level" : 1,
    "move" : "Fairy Wind"
  }, {
    "level" : 1,
    "move" : "Mega Drain"
  }, {
    "level" : 1,
    "move" : "Pollen Puff"
  }, {
    "level" : 1,
    "move" : "Struggle Bug"
  }, {
    "level" : 1,
    "move" : "Stun Spore"
  }, {
    "level" : 4,
    "move" : "Fairy Wind"
  }, {
    "level" : 7,
    "move" : "Stun Spore"
  }, {
    "level" : 10,
    "move" : "Struggle Bug"
  }, {
    "level" : 13,
    "move" : "Silver Wind"
  }, {
    "level" : 16,
    "move" : "Draining Kiss"
  }, {
    "level" : 21,
    "move" : "Sweet Scent"
  }, {
    "level" : 25,
    "move" : "Pollen Puff"
  }, {
    "level" : 28,
    "move" : "Bug Buzz"
  }, {
    "level" : 35,
    "move" : "Dazzling Gleam"
  }, {
    "level" : 42,
    "move" : "Aromatherapy"
  }, {
    "level" : 49,
    "move" : "Quiver Dance"
  }, {
    "level" : 52,
    "move" : "Moonblast"
  }, {
    "level" : 55,
    "move" : "Alluring Voice"
  } ],
  "eggMoves" : [ "Baton Pass", "Bestow", "Moonblast", "Powder", "Skill Swap", "Speed Swap", "Sticky Web" ],
  "teachableMoves" : [ "Acrobatics", "Aerial Ace", "Attract", "Calm Mind", "Covet", "Dazzling Gleam", "Defog", "Double Team", "Dream Eater", "Dual Wingbeat", "Endure", "Energy Ball", "Facade", "Giga Impact", "Grass Knot", "Hyper Beam", "Leech Life", "Light Screen", "Play Rough", "Protect", "Psych Up", "Psychic", "Reflect", "Rest", "Roost", "Safeguard", "Silver Wind", "Sleep Talk", "Snore", "Solar Beam", "Sunny Day", "Swagger", "Swift", "Thief", "Toxic", "Trailblaze", "U Turn" ],
  "encounters" : [ {
    "area" : "Lilycove City",
    "bucket" : "Land",
    "rateBase" : 10,
    "min" : 53,
    "max" : 55,
    "slot" : 3
  } ]
}