{
  "dex" : 707,
  "speciesId" : "SPECIES_ARMAROUGE",
  "name" : "Armarouge",
  "types" : [ "Fire", "Psychic" ],
  "abilities" : [ "Flash Fire", "None", "Weak Armor" ],
  "evYield" : {
    "spa" : 2
  },
  "malePct" : 50.0,
  "femalePct" : 50.0,
  "catchRate" : 25,
  "baseExp" : 263,
  "eggGroups" : [ "Human Like" ],
  "hatchSteps" : 8960,
  "heightM" : 1.5,
  "weightKg" : 85.0,
  "growthRate" : "Slow",
  "color" : "Red",
  "category" : "Fire Warrior",
  "friendship" : 20,
  "description" : "Armarouge evolved through the use\nof a set of armor that belonged to\na distinguished warrior. This\nPokémon is incredibly loyal.",
  "preEvolutionId" : "SPECIES_CHARCADET",
  "evolution" : [ ],
  "baseStats" : {
    "hp" : 85,
    "atk" : 60,
    "def" : 100,
    "spe" : 75,
    "spa" : 125,
    "spd" : 80
  },
  "heldItems" : { },
  "levelUpMoves" : [ {
    "level" : 0,
    "move" : "Psyshock"
  }, {
    "level" : 1,
    "move" : "Astonish"
  }, {
    "level" : 1,
    "move" : "Ember"
  }, {
    "level" : 1,
    "move" : "Mystical Fire"
  }, {
    "level" : 1,
    "move" : "Psyshock"
  }, {
    "level" : 1,
    "move" : "Wide Guard"
  }, {
    "level" : 8,
    "move" : "Clear Smog"
  }, {
    "level" : 11,
    "move" : "Fire Spin"
  }, {
    "level" : 16,
    "move" : "Will O Wisp"
  }, {
    "level" : 22,
    "move" : "Night Shade"
  }, {
    "level" : 24,
    "move" : "Flame Wheel"
  }, {
    "level" : 28,
    "move" : "Incinerate"
  }, {
    "level" : 33,
    "move" : "Lava Plume"
  }, {
    "level" : 35,
    "move" : "Calm Mind"
  }, {
    "level" : 40,
    "move" : "Flamethrower"
  }, {
    "level" : 45,
    "move" : "Expanding Force"
  }, {
    "level" : 48,
    "move" : "Armor Cannon"
  }, {
    "level" : 52,
    "move" : "Aura Sphere"
  }, {
    "level" : 54,
    "move" : "Dark Pulse"
  }, {
    "level" : 58,
    "move" : "Dragon Pulse"
  }, {
    "level" : 61,
    "move" : "Flash Cannon"
  }, {
    "level" : 66,
    "move" : "Meteor Beam"
  }, {
    "level" : 70,
    "move" : "Psychic"
  } ],
  "eggMoves" : [ "Destiny Bond", "Disable", "Spite" ],
  "teachableMoves" : [ "Aura Sphere", "Calm Mind", "Dark Pulse", "Dragon Pulse", "Endure", "Energy Ball", "Facade", "Fire Blast", "Flamethrower", "Flash Cannon", "Focus Blast", "Iron Defense", "Light Screen", "Meteor Beam", "Mystical Fire", "Overheat", "Protect", "Psych Up", "Psychic", "Psyshock", "Reflect", "Rest", "Shadow Ball", "Sleep Talk", "Solar Beam", "Sunny Day", "Taunt", "Trick Room", "Will O Wisp" ],
  "encounters" : [ {
    "area" : "Route 123",
    "bucket" : "Land",
    "rateBase" : 20,
    "min" : 52,
    "max" : 55,
    "slot" : 8
  }, {
    "area" : "Mossdeep City",
    "bucket" : "Land",
    "rateBase" : 10,
    "min" : 67,
    "max" : 69,
    "slot" : 11
  }, {
    "area" : "Scorched Slab0",
    "bucket" : "Land",
    "rateBase" : 20,
    "min" : 51,
    "max" : 54,
    "slot" : 2
  } ]
}