{
  "SPECIES_ROTOM_FAN": "Rotom Fan",
  "SPECIES_ROTOM_FROST": "Rotom Frost",
  "SPECIES_ROTOM_HEAT": "Rotom Heat",
  "SPECIES_ROTOM_MOW": "Rotom Mow",
  "SPECIES_ROTOM_WASH": "Rotom Wash",

  "SPECIES_CASTFORM_RAINY": "Castform Rainy",
  "SPECIES_CASTFORM_SNOWY": "Castform Snowy",
  "SPECIES_CASTFORM_SUNNY": "Castform Sunny",

  "SPECIES_BASCULIN_WHITE_STRIPED": "Hisuian Basculin",
  "SPECIES_BASCULEGION_FEMALE": "Basculegion♀",
  "SPECIES_BASCULEGION_MALE": "Basculegion♂",

  "SPECIES_URSALUNA_BLOODMOON": "Ursaluna Bloodmoon"
}